 [
    {
      "id": "brayden-law-1407613-unsplash.jpg",
      "title": null,
      "filename": "brayden-law-1407613-unsplash.jpg",
      "location": "The Broad, Los Angeles, United States of America",
      "source": {
        "name": "Unsplash",
        "url": "https://unsplash.com"
      },
      "photographer": {
        "name": "Brayden Law",
        "url": "https://unsplash.com/@braydenlaw"
      }
    },
    {
      "id": "yann-allegre-1408153-unsplash.jpg",
      "title": null,
      "filename": "yann-allegre-1408153-unsplash.jpg",
      "location": null,
      "source": {
        "name": "Unsplash",
        "url": "https://unsplash.com"
      },
      "photographer": {
        "name": "Yann Allegre",
        "url": "https://unsplash.com/@yann_allegre"
      }
    }
  ]
